huaweicloudsdkidmeclassicapi/__init__.py
huaweicloudsdkidmeclassicapi/v1/__init__.py
huaweicloudsdkidmeclassicapi/v1/idmeclassicapi_async_client.py
huaweicloudsdkidmeclassicapi/v1/idmeclassicapi_client.py
huaweicloudsdkidmeclassicapi/v1/model/__init__.py
huaweicloudsdkidmeclassicapi/v1/model/add_tag_request.py
huaweicloudsdkidmeclassicapi/v1/model/add_tag_response.py
huaweicloudsdkidmeclassicapi/v1/model/add_to_category_request.py
huaweicloudsdkidmeclassicapi/v1/model/add_to_category_response.py
huaweicloudsdkidmeclassicapi/v1/model/basic_object_query_view_dto.py
huaweicloudsdkidmeclassicapi/v1/model/batch_add_child_node_request.py
huaweicloudsdkidmeclassicapi/v1/model/batch_add_child_node_response.py
huaweicloudsdkidmeclassicapi/v1/model/batch_checkin_request.py
huaweicloudsdkidmeclassicapi/v1/model/batch_checkin_response.py
huaweicloudsdkidmeclassicapi/v1/model/batch_checkout_and_update_request.py
huaweicloudsdkidmeclassicapi/v1/model/batch_checkout_and_update_response.py
huaweicloudsdkidmeclassicapi/v1/model/batch_checkout_request.py
huaweicloudsdkidmeclassicapi/v1/model/batch_checkout_response.py
huaweicloudsdkidmeclassicapi/v1/model/batch_checkout_undo_by_admin_request.py
huaweicloudsdkidmeclassicapi/v1/model/batch_checkout_undo_by_admin_response.py
huaweicloudsdkidmeclassicapi/v1/model/batch_checkout_undo_request.py
huaweicloudsdkidmeclassicapi/v1/model/batch_checkout_undo_response.py
huaweicloudsdkidmeclassicapi/v1/model/batch_create_share_docs_request.py
huaweicloudsdkidmeclassicapi/v1/model/batch_create_share_docs_response.py
huaweicloudsdkidmeclassicapi/v1/model/batch_create_using_post_request.py
huaweicloudsdkidmeclassicapi/v1/model/batch_create_using_post_response.py
huaweicloudsdkidmeclassicapi/v1/model/batch_create_view_request.py
huaweicloudsdkidmeclassicapi/v1/model/batch_create_view_response.py
huaweicloudsdkidmeclassicapi/v1/model/batch_delete_branch_request.py
huaweicloudsdkidmeclassicapi/v1/model/batch_delete_branch_response.py
huaweicloudsdkidmeclassicapi-3.1.184.dist-info/METADATA
huaweicloudsdkidmeclassicapi-3.1.184.dist-info/WHEEL
huaweicloudsdkidmeclassicapi-3.1.184.dist-info/licenses/LICENSE
huaweicloudsdkidmeclassicapi-3.1.184.dist-info/RECORD
